{"chunk_definitions":[{"row":9,"row_count":1,"visible":true,"expansion_state":0,"options":{"engine":"r","label":"unnamed-chunk-8"},"document_id":"8CD97FF0","chunk_id":"crj0dcq6oru8z","chunk_label":"unnamed-chunk-1"},{"row":15,"row_count":1,"visible":true,"expansion_state":0,"options":{"engine":"r","label":"unnamed-chunk-9"},"document_id":"8CD97FF0","chunk_id":"cdt1cqj1ed7t9","chunk_label":"unnamed-chunk-2"},{"row":21,"row_count":1,"visible":true,"expansion_state":0,"options":{"engine":"r","label":"unnamed-chunk-10"},"document_id":"8CD97FF0","chunk_id":"cwg0xv5hh2lap","chunk_label":"unnamed-chunk-3"},{"row":28,"row_count":1,"visible":true,"expansion_state":0,"options":{"engine":"r","label":"unnamed-chunk-12"},"document_id":"8CD97FF0","chunk_id":"cl0t9dsbqvdpl","chunk_label":"unnamed-chunk-4"}],"doc_write_time":2963636341936}